{
  "movies": [
    {
      "id": 1,
      "title": "The Rum Diary",
      "director": "Bruce Robinson",
      "duration": "120",
      "price": "48.66",
      "img": "https://kbimages1-a.akamaihd.net/6feeffad-38a1-45ed-a001-7763c87615c0/1200/1200/False/the-rum-diary-a-screenplay.jpg",
      "featured": false,
      "description": "The Rum Diary is a 2011 American comedy-drama film written and directed by Bruce Robinson, based on the 1998 novel of the same name by Hunter S. Thompson."
    },
    {
      "id": 882,
      "title": "Free Guy",
      "director": "Murray Fahey",
      "duration": "130",
      "price": 31.2,
      "img": "https://lumiere-a.akamaihd.net/v1/images/p_20cs_freeguy_homeent_21930_49e74453.jpeg?region=0%2C0%2C540%2C810",
      "featured": true,
      "description": "In the extremely popular video game, Free City, a NPC named Guy learns the true nature of his existence when he meets the girl of his dreams, a human player. This player's interactions with Guy has massive affects on him, the game, and real world as they play it."
    },
    {
      "id": 947,
      "title": "Fight Club",
      "director": "David Fincher",
      "duration": "145",
      "price": "122",
      "img": "https://makeout.space/uploads/posts/2016-05/1462286899_fight_club_rvb_72.jpg",
      "featured": false,
      "description": "Unhappy with his capitalistic lifestyle, a white-collared insomniac forms an underground fight club with Tyler, a careless soap salesman. Soon, their venture spirals down into something sinister."
    },
    {
      "id": 296.7827449490159,
      "title": "Wednesday",
      "director": "Alfred Gough, Miles Millar",
      "duration": "8",
      "price": "100",
      "img": "https://upload.wikimedia.org/wikipedia/ru/thumb/b/b2/%D0%A3%D1%8D%D0%BD%D1%81%D0%B4%D0%B5%D0%B9%D0%9F%D0%BE%D1%81%D1%82%D0%B5%D1%80.jpg/405px-%D0%A3%D1%8D%D0%BD%D1%81%D0%B4%D0%B5%D0%B9%D0%9F%D0%BE%D1%81%D1%82%D0%B5%D1%80.jpg",
      "featured": false,
      "description": "Smart, sarcastic and a little dead inside, Wednesday Addams investigates a murder spree while making new friends — and foes — at Nevermore Academy."
    },
    {
      "id": 438.9959967806092,
      "title": "Drive",
      "director": " Nicolas Winding Refn",
      "duration": "90",
      "price": "22",
      "img": "https://professionalmorondotcom.files.wordpress.com/2021/04/drive.jpg",
      "featured": false,
      "description": "A mysterious Hollywood action film stuntman gets in trouble with gangsters when he tries to help his neighbor's husband rob a pawn shop while serving as his getaway driver."
    },
    {
      "id": 452.6099198076918,
      "title": "Interstellar",
      "director": "Christopher Nolan",
      "duration": "100",
      "price": "55",
      "img": "https://pics.filmaffinity.com/Interstellar-366875261-large.jpg",
      "featured": false,
      "description": "When Earth becomes uninhabitable in the future, a farmer and ex-NASA pilot, Joseph Cooper, is tasked to pilot a spacecraft, along with a team of researchers, to find a new planet for humans."
    },
    {
      "id": 551.4683348749177,
      "title": "Tenet",
      "director": "Christopher Nolan",
      "duration": "180",
      "price": "55",
      "img": "https://m.media-amazon.com/images/M/MV5BNDhiODUyN2UtYTQzZi00YTE0LWJiMWEtYTVlODEyZDQwYzRhXkEyXkFqcGdeQXVyMTA3MDk2NDg2._V1_.jpg",
      "featured": false,
      "description": "When a few objects that can be manipulated and used as weapons in the future fall into the wrong hands, a CIA operative, known as the Protagonist, must save the world."
    },
    {
      "id": 892.2407791216971,
      "title": "Inglourious Basterds",
      "director": "Quentin Tarantino",
      "duration": "190",
      "price": "77",
      "img": "https://m.media-amazon.com/images/M/MV5BOTJiNDEzOWYtMTVjOC00ZjlmLWE0NGMtZmE1OWVmZDQ2OWJhXkEyXkFqcGdeQXVyNTIzOTk5ODM@._V1_FMjpg_UX1000_.jpg",
      "featured": false,
      "description": "A few Jewish soldiers are on an undercover mission to bring down the Nazi government and put an end to the war. Meanwhile, a woman wants to avenge the death of her family from a German officer."
    }
  ],
  "users": [
    {
      "id": 22,
      "email": "test",
      "password": "test",
      "firstName": "A",
      "lastName": "A",
      "isAdmin": false
    },
    {
      "id": 32,
      "email": "test2@gmail.com",
      "password": "test2",
      "firstName": "ALLA",
      "lastName": "HON",
      "isAdmin": false
    }
  ]
}